BetterryguysFirstPackage/__init__.py
BetterryguysFirstPackage/add.py
BetterryguysFirstPackage/subtract.py
BetterryguysFirstPackage/extras/__init__.py
BetterryguysFirstPackage/extras/divide.py
BetterryguysFirstPackage/extras/multiply.py
BetterryguysFirstPackage/extras/power.py
amatiCalpackage/__init__.py
amatiCalpackage/add.py
amatiCalpackage/subtract.py
amatiCalpackage/extras/__init__.py
amatiCalpackage/extras/divide.py
amatiCalpackage/extras/multiply.py
matiCalpackage/__init__.py
matiCalpackage/add.py
matiCalpackage/subtract.py
matiCalpackage/extras/__init__.py
matiCalpackage/extras/divide.py
matiCalpackage/extras/multiply.py
BetterryguysFirstPackage-0.0.6.dist-info/METADATA
BetterryguysFirstPackage-0.0.6.dist-info/WHEEL
BetterryguysFirstPackage-0.0.6.dist-info/top_level.txt
BetterryguysFirstPackage-0.0.6.dist-info/RECORD
